jupyter_black/__init__.py
jupyter_black/jupyter_black.py
jupyter_black-0.4.0.dist-info/AUTHORS.md
jupyter_black-0.4.0.dist-info/LICENSE
jupyter_black-0.4.0.dist-info/METADATA
jupyter_black-0.4.0.dist-info/WHEEL
jupyter_black-0.4.0.dist-info/top_level.txt
jupyter_black-0.4.0.dist-info/RECORD
