Metadata-Version: 2.1
Name: jupyter-black
Version: 0.4.0
Summary: A simple extension for Jupyter Notebook and Jupyter Lab to beautify Python code automatically using Black. Fork of dnanhkhoa/nb_black.
Author-email: Nathan Henrie <nate@n8henrie.com>
License: MIT
Project-URL: homepage, https://github.com/n8henrie/jupyter-black
Keywords: jupyter-black
Classifier: Programming Language :: Python :: 3
Classifier: Programming Language :: Python :: 3.8
Classifier: Programming Language :: Python :: 3.9
Classifier: Programming Language :: Python :: 3.10
Classifier: Programming Language :: Python :: 3.11
License-File: LICENSE
License-File: AUTHORS.md
Requires-Dist: black[jupyter]>=21
Provides-Extra: test
Requires-Dist: flake8==7; extra == "test"
Requires-Dist: flake8-docstrings==1.7; extra == "test"
Requires-Dist: jupyterlab>=4; extra == "test"
Requires-Dist: mypy==1; extra == "test"
Requires-Dist: notebook>=7; extra == "test"
Requires-Dist: pep8-naming==0.14; extra == "test"
Requires-Dist: playwright==1.46; extra == "test"
Requires-Dist: pytest==8; extra == "test"
Requires-Dist: tox==4; extra == "test"
Provides-Extra: dev
Requires-Dist: build==1; extra == "dev"
Requires-Dist: twine==5; extra == "dev"
